[
  {
    "stateName": "login",
    "urlPrefix": "/login",
    "type": "load",
    "src": "app/login/login"
  }
  ,{
    "stateName": "signup",
    "urlPrefix": "/signup",
    "type": "load",
    "src": "app/signup/signup"
  }
  ,{
    "stateName": "admin",
    "urlPrefix": "/admin",
    "type": "load",
    "src": "app/admin/admin"
  }
  ,{
    "stateName": "home",
    "urlPrefix": "/home",
    "type": "load",
    "src": "app/home/home"
  }
  ,{
    "stateName": "core",
    "urlPrefix": "/core",
    "type": "load",
    "src": "app/core/core"
  }
  ,{
    "stateName": "banes",
    "urlPrefix": "/banes",
    "type": "load",
    "src": "app/banes/banes"
  }
  ,{
    "stateName": "boons",
    "urlPrefix": "/boons",
    "type": "load",
    "src": "app/boons/boons"
  }
  ,{
    "stateName": "feats",
    "urlPrefix": "/feats",
    "type": "load",
    "src": "app/feats/feats"
  },
  ,{
    "stateName": "commercialTerms",
    "urlPrefix": "/commercial-terms",
    "type": "load",
    "src": "app/commercialTerms/commercialTerms"
  },
  ,{
    "stateName": "noncommercialTerms",
    "urlPrefix": "/noncommercial-terms",
    "type": "load",
    "src": "app/noncommercialTerms/noncommercialTerms"
  },{
    "stateName": "license",
    "urlPrefix": "/community-license",
    "type": "load",
    "src": "app/license/license"
  }
]
